kepler/__init__.py
kepler/cli.py
kepler/agents/__init__.py
kepler/agents/coding_agent.py
kepler/agents/react_agent.py
kepler/core/__init__.py
kepler/core/agent.py
kepler/core/config.py
kepler/core/llm_providers.py
kepler/core/tools.py
kepler_ai-0.1.3.dist-info/licenses/LICENSE
kepler_ai-0.1.3.dist-info/METADATA
kepler_ai-0.1.3.dist-info/WHEEL
kepler_ai-0.1.3.dist-info/entry_points.txt
kepler_ai-0.1.3.dist-info/top_level.txt
kepler_ai-0.1.3.dist-info/RECORD
