Metadata-Version: 2.4
Name: kepler-ai
Version: 0.1.3
Summary: A powerful, flexible framework for building AI agents with multiple LLM support, function calling, and ReAct reasoning capabilities
Author-email: Sandeep Chakraborty <heyitssandeep@gmail.com>
Maintainer-email: Sandeep Chakraborty <heyitssandeep@gmail.com>
License-Expression: MIT
Project-URL: Homepage, https://github.com/sandeep-chakraborty/kepler
Keywords: ai,agents,llm,react,openai,anthropic,gemini,framework
Classifier: Development Status :: 3 - Alpha
Classifier: Intended Audience :: Developers
Classifier: Operating System :: OS Independent
Classifier: Programming Language :: Python :: 3
Classifier: Programming Language :: Python :: 3.8
Classifier: Programming Language :: Python :: 3.9
Classifier: Programming Language :: Python :: 3.10
Classifier: Programming Language :: Python :: 3.11
Classifier: Programming Language :: Python :: 3.12
Classifier: Topic :: Scientific/Engineering :: Artificial Intelligence
Classifier: Topic :: Software Development :: Libraries :: Python Modules
Requires-Python: >=3.8
License-File: LICENSE
Requires-Dist: pydantic>=2.0.0
Requires-Dist: python-dotenv>=1.0.0
Requires-Dist: requests>=2.25.0
Requires-Dist: PyYAML>=6.0
Provides-Extra: openai
Requires-Dist: openai>=1.0.0; extra == "openai"
Provides-Extra: anthropic
Requires-Dist: anthropic>=0.25.0; extra == "anthropic"
Provides-Extra: gemini
Requires-Dist: google-genai>=0.3.0; extra == "gemini"
Provides-Extra: serpapi
Requires-Dist: google-search-results>=2.4.0; extra == "serpapi"
Provides-Extra: all
Requires-Dist: openai>=1.0.0; extra == "all"
Requires-Dist: anthropic>=0.25.0; extra == "all"
Requires-Dist: google-genai>=0.3.0; extra == "all"
Requires-Dist: google-search-results>=2.4.0; extra == "all"
Provides-Extra: dev
Requires-Dist: pytest>=7.0.0; extra == "dev"
Requires-Dist: pytest-cov>=4.0.0; extra == "dev"
Requires-Dist: black>=23.0.0; extra == "dev"
Requires-Dist: isort>=5.12.0; extra == "dev"
Requires-Dist: flake8>=6.0.0; extra == "dev"
Requires-Dist: mypy>=1.0.0; extra == "dev"
Requires-Dist: pre-commit>=3.0.0; extra == "dev"
Dynamic: license-file
